gfw_creator/__init__.py
gfw_creator/cli.py
gfw_creator/esm_tools_plugin.py
gfw_creator/gfw_creator.py
gfw_creator/data/gfw_atmo_template.nc
gfw_creator-0.2.2.dist-info/AUTHORS.rst
gfw_creator-0.2.2.dist-info/LICENSE
gfw_creator-0.2.2.dist-info/METADATA
gfw_creator-0.2.2.dist-info/WHEEL
gfw_creator-0.2.2.dist-info/entry_points.txt
gfw_creator-0.2.2.dist-info/top_level.txt
gfw_creator-0.2.2.dist-info/RECORD
