Metadata-Version: 2.1
Name: gfw-creator
Version: 0.2.2
Summary: GFW Creator allows you to generate files for the gfw_atmo switch in ECHAM6/JSBACH of AWI-ESM
Home-page: https://github.com/pgierz/gfw_creator
Author: Paul Gierz
Author-email: pgierz@awi.de
License: GNU General Public License v3
Keywords: gfw_creator
Platform: UNKNOWN
Classifier: Development Status :: 2 - Pre-Alpha
Classifier: Intended Audience :: Developers
Classifier: License :: OSI Approved :: GNU General Public License v3 (GPLv3)
Classifier: Natural Language :: English
Classifier: Programming Language :: Python :: 3.6
Requires-Dist: Click (>=6.0)
Requires-Dist: xarray
Requires-Dist: cdo
Requires-Dist: netcdf4
